{"dependencies":[{"name":"C:\\Users\\Radas\\Desktop\\assigment\\node_modules\\babel-runtime\\node_modules\\core-js\\package.json","includedInParent":true,"mtime":1544636853549},{"name":"C:\\Users\\Radas\\Desktop\\assigment\\package.json","includedInParent":true,"mtime":1530021218000}],"generated":{"js":"exports.f = Object.getOwnPropertySymbols;\n","map":{"mappings":[{"source":"node_modules\\babel-runtime\\node_modules\\core-js\\library\\modules\\_object-gops.js","original":{"line":1,"column":0},"generated":{"line":1,"column":0}},{"source":"node_modules\\babel-runtime\\node_modules\\core-js\\library\\modules\\_object-gops.js","original":{"line":2,"column":0},"generated":{"line":2,"column":0}}],"sources":{"node_modules\\babel-runtime\\node_modules\\core-js\\library\\modules\\_object-gops.js":"exports.f = Object.getOwnPropertySymbols;\n"},"lineCount":2}},"hash":"c50c4a976875dc9a2e64729505a7fe19","cacheData":{"env":{}},"id":291}